gnome_dns_switcher/__init__.py
gnome_dns_switcher/__main__.py
gnome_dns_switcher/gnome_helpers/__init__.py
gnome_dns_switcher/gnome_helpers/async_call.py
gnome_dns_switcher/gnome_helpers/indicator.py
gnome_dns_switcher/gnome_helpers/nmcli.py
gnome_dns_switcher/switcher/__init__.py
gnome_dns_switcher/switcher/dnsswitcher.py
gnome_dns_switcher/switcher/server.py
gnome_dns_switcher-1.4.0.dist-info/licenses/LICENSE
gnome_dns_switcher-1.4.0.dist-info/METADATA
gnome_dns_switcher-1.4.0.dist-info/WHEEL
gnome_dns_switcher-1.4.0.dist-info/entry_points.txt
gnome_dns_switcher-1.4.0.dist-info/top_level.txt
gnome_dns_switcher-1.4.0.dist-info/RECORD
