Metadata-Version: 2.4
Name: gnome-dns-switcher
Version: 1.4.0
Summary: DNS Switcher for Ubuntu Gnome
Author: Anner Visser
Author-email: mail@annervisser.nl
Maintainer: Anner Visser
Maintainer-email: mail@annervisser.nl
License: GPLv3
Project-URL: Source, https://github.com/annervisser/gnome-appindicator-dns-switcher/
Project-URL: Issues, https://github.com/annervisser/gnome-appindicator-dns-switcher/issues
Keywords: gnome,ubuntu,dns,appindicator
Classifier: Intended Audience :: Information Technology
Classifier: License :: OSI Approved :: GNU General Public License v3 (GPLv3)
Classifier: Operating System :: POSIX :: Linux
Classifier: Programming Language :: Python :: 3
Classifier: Topic :: Utilities
Requires-Python: >=3.6
License-File: LICENSE
Requires-Dist: pyyaml>=5
Requires-Dist: PyGObject<3.51.0,>=3.36.0
Requires-Dist: pycairo>=1.16.0
Requires-Dist: six<2,>=1.9.0
Dynamic: license-file
